column_classifier/__init__.py
column_classifier/column_classifier.py
tabular_column_classifier-0.3.0.dist-info/licenses/LICENSE
tabular_column_classifier-0.3.0.dist-info/METADATA
tabular_column_classifier-0.3.0.dist-info/WHEEL
tabular_column_classifier-0.3.0.dist-info/top_level.txt
tabular_column_classifier-0.3.0.dist-info/RECORD
