Metadata-Version: 2.4
Name: tabular-column-classifier
Version: 0.3.0
Summary: Fast spaCy-based column classifier with optional LLM refinement.
Home-page: https://github.com/roby-avo/tabular-column-classifier
Author: Roberto Avogadro
Author-email: roberto.avogadro@sintef.no
License: Apache License 2.0
Project-URL: Source, https://github.com/roby-avo/tabular-column-classifier
Project-URL: Issues, https://github.com/roby-avo/tabular-column-classifier/issues
Classifier: Development Status :: 4 - Beta
Classifier: Intended Audience :: Developers
Classifier: License :: OSI Approved :: Apache Software License
Classifier: Programming Language :: Python :: 3
Classifier: Programming Language :: Python :: 3.8
Classifier: Programming Language :: Python :: 3.9
Classifier: Programming Language :: Python :: 3.10
Classifier: Programming Language :: Python :: 3.11
Requires-Python: >=3.8
License-File: LICENSE
Requires-Dist: pandas>=1.4
Requires-Dist: spacy>=3.7.5
Provides-Extra: llm
Requires-Dist: ollama>=0.3.0; extra == "llm"
Dynamic: author
Dynamic: author-email
Dynamic: classifier
Dynamic: description
Dynamic: description-content-type
Dynamic: home-page
Dynamic: license
Dynamic: license-file
Dynamic: project-url
Dynamic: provides-extra
Dynamic: requires-dist
Dynamic: requires-python
Dynamic: summary
